feat_psu/__init__.py
feat_psu/feat.py
feat_psu/feat_ghg.py
feat_psu/feat_nrg.py
feat_psu/feat_util.py
feat_psu/tests/__init__.py
feat_psu/tests/test_feat.py
feat_psu-0.3.1.dist-info/.ipynb_checkpoints/PKG-INFO-checkpoint
feat_psu-0.3.1.dist-info/.ipynb_checkpoints/SOURCES-checkpoint.txt
feat_psu-0.3.1.dist-info/LICENSE
feat_psu-0.3.1.dist-info/METADATA
feat_psu-0.3.1.dist-info/WHEEL
feat_psu-0.3.1.dist-info/top_level.txt
feat_psu-0.3.1.dist-info/RECORD
